ground_control/__init__.py
ground_control/app.py
ground_control/main.py
ground_control/cli/__init__.py
ground_control/cli/process_list.py
ground_control/utils/__init__.py
ground_control/utils/formatting.py
ground_control/utils/system_metrics.py
ground_control/widgets/__init__.py
ground_control/widgets/base.py
ground_control/widgets/cpu.py
ground_control/widgets/disk.py
ground_control/widgets/gpu.py
ground_control/widgets/network.py
albe-0.0.2.dist-info/LICENSE
albe-0.0.2.dist-info/METADATA
albe-0.0.2.dist-info/WHEEL
albe-0.0.2.dist-info/top_level.txt
albe-0.0.2.dist-info/RECORD
